procedure/__init__.py
procedure/decorators.py
procedure/models.py
procedure/migrations/0001_initial.py
procedure/migrations/0002_procedure_executed_alter_procedure_parent.py
procedure/migrations/0003_procedure_logs.py
procedure/migrations/0004_alter_procedure_id.py
procedure/migrations/0005_procedure_c_at_procedure_exception_procedure_level_and_more.py
procedure/migrations/0006_alter_procedure_results.py
procedure/migrations/__init__.py
django_procedure-0.4.2.dist-info/LICENSE
django_procedure-0.4.2.dist-info/METADATA
django_procedure-0.4.2.dist-info/WHEEL
django_procedure-0.4.2.dist-info/top_level.txt
django_procedure-0.4.2.dist-info/RECORD
